validation/__init__.py
validation/constants/rules.py
validation/constants/types.py
validation/exceptions/__init__.py
validation/exceptions/array_validation_error.py
validation/exceptions/base_error.py
validation/exceptions/error.py
validation/exceptions/nullable_error.py
validation/exceptions/object_validation_error.py
validation/exceptions/rule_error.py
validation/exceptions/spec_error.py
validation/exceptions/type_error.py
validation/exceptions/validation_error.py
validation/parser/__init__.py
validation/parser/spec_parser.py
validation/rules/__init__.py
validation/rules/alpha.py
validation/rules/alphadash.py
validation/rules/alphanum.py
validation/rules/between.py
validation/rules/betweenlength.py
validation/rules/decimal.py
validation/rules/equals.py
validation/rules/equalsto.py
validation/rules/fileformat.py
validation/rules/filetype.py
validation/rules/hex.py
validation/rules/isin.py
validation/rules/len.py
validation/rules/max.py
validation/rules/maxlength.py
validation/rules/maxsize.py
validation/rules/min.py
validation/rules/minlength.py
validation/rules/minsize.py
validation/rules/mustbetrue.py
validation/rules/nullableif.py
validation/rules/phonetype.py
validation/rules/regex.py
validation/rules/required.py
validation/rules/rule.py
validation/rules/rule_factory.py
validation/rules/strict.py
validation/types/__init__.py
validation/types/array.py
validation/types/base58.py
validation/types/base64.py
validation/types/base64file.py
validation/types/boolean.py
validation/types/composite.py
validation/types/email.py
validation/types/float.py
validation/types/integer.py
validation/types/iso8601date.py
validation/types/object.py
validation/types/phone.py
validation/types/sequence.py
validation/types/string.py
validation/types/type.py
validation/types/type_factory.py
validation/types/url.py
validation/types/uuid.py
validation/utils/__init__.py
validation/utils/base64file_utils.py
validation/validator/__init__.py
validation/validator/validator_factory.py
moveax_validation-2.0.0.dist-info/LICENSE
moveax_validation-2.0.0.dist-info/WHEEL
moveax_validation-2.0.0.dist-info/METADATA
moveax_validation-2.0.0.dist-info/RECORD
