Metadata-Version: 2.1
Name: moveax-validation
Version: 2.0.0
Summary: Python implementation of our validation library
Home-page: https://github.com/moveaxlab/validation-py/
License: MIT
Keywords: schema,validation
Author: Mattias E. Mignone
Author-email: mattias.mignone@moveax.it
Requires-Python: >=3.5,<4.0
Classifier: License :: OSI Approved :: MIT License
Classifier: Programming Language :: Python :: 3
Classifier: Programming Language :: Python :: 3.5
Classifier: Programming Language :: Python :: 3.6
Classifier: Programming Language :: Python :: 3.7
Classifier: Programming Language :: Python :: 3.8
Requires-Dist: phonenumbers (>=8.10,<9.0)
Requires-Dist: python-dateutil (>=2.7.3,<3.0.0)
Project-URL: Repository, https://github.com/moveaxlab/validation-py/
